source/__init__.py
source/__main__.py
source/env.py
source/solc_parse.py
solc_parser-1.0.4.dist-info/LICENSE
solc_parser-1.0.4.dist-info/METADATA
solc_parser-1.0.4.dist-info/WHEEL
solc_parser-1.0.4.dist-info/entry_points.txt
solc_parser-1.0.4.dist-info/top_level.txt
solc_parser-1.0.4.dist-info/RECORD
