Metadata-Version: 2.1
Name: solc-parser
Version: 1.0.4
Summary: Solc Automated Parser and Installation Tool
Home-page: https://github.com/siksum/Solc-Parser
Author: Namryeong Kim
Author-email: Namryeong Kim <namyoung0718@google.com>
Project-URL: Homepage, https://github.com/siksum/Solc-Parser
Project-URL: Bug Tracker, https://github.com/siksum/Solc-Parser/issues
Classifier: Programming Language :: Python :: 3
Classifier: License :: OSI Approved :: GNU General Public License v3 (GPLv3)
Classifier: Operating System :: OS Independent
Requires-Python: >=3.8
License-File: LICENSE
